odoo/addons/shopfloor_base/README.rst
odoo/addons/shopfloor_base/__init__.py
odoo/addons/shopfloor_base/__manifest__.py
odoo/addons/shopfloor_base/hooks.py
odoo/addons/shopfloor_base/utils.py
odoo/addons/shopfloor_base/actions/__init__.py
odoo/addons/shopfloor_base/actions/base_action.py
odoo/addons/shopfloor_base/actions/data.py
odoo/addons/shopfloor_base/actions/data_detail.py
odoo/addons/shopfloor_base/actions/message.py
odoo/addons/shopfloor_base/actions/savepoint.py
odoo/addons/shopfloor_base/actions/schema.py
odoo/addons/shopfloor_base/actions/schema_detail.py
odoo/addons/shopfloor_base/actions/search.py
odoo/addons/shopfloor_base/controllers/__init__.py
odoo/addons/shopfloor_base/controllers/main.py
odoo/addons/shopfloor_base/data/module_category_data.xml
odoo/addons/shopfloor_base/demo/auth_api_key_demo.xml
odoo/addons/shopfloor_base/demo/shopfloor_menu_demo.xml
odoo/addons/shopfloor_base/demo/shopfloor_profile_demo.xml
odoo/addons/shopfloor_base/demo/shopfloor_scenario_demo.xml
odoo/addons/shopfloor_base/i18n/shopfloor_base.pot
odoo/addons/shopfloor_base/models/__init__.py
odoo/addons/shopfloor_base/models/shopfloor_menu.py
odoo/addons/shopfloor_base/models/shopfloor_profile.py
odoo/addons/shopfloor_base/models/shopfloor_scenario.py
odoo/addons/shopfloor_base/readme/CONFIGURE.rst
odoo/addons/shopfloor_base/readme/CONTRIBUTORS.rst
odoo/addons/shopfloor_base/readme/CREDITS.rst
odoo/addons/shopfloor_base/readme/DESCRIPTION.rst
odoo/addons/shopfloor_base/readme/HISTORY.rst
odoo/addons/shopfloor_base/readme/ROADMAP.rst
odoo/addons/shopfloor_base/readme/USAGE.rst
odoo/addons/shopfloor_base/security/groups.xml
odoo/addons/shopfloor_base/security/ir.model.access.csv
odoo/addons/shopfloor_base/services/__init__.py
odoo/addons/shopfloor_base/services/app.py
odoo/addons/shopfloor_base/services/menu.py
odoo/addons/shopfloor_base/services/profile.py
odoo/addons/shopfloor_base/services/scan_anything.py
odoo/addons/shopfloor_base/services/service.py
odoo13_addon_shopfloor_base-13.0.1.1.0.dist-info/METADATA
odoo13_addon_shopfloor_base-13.0.1.1.0.dist-info/WHEEL
odoo13_addon_shopfloor_base-13.0.1.1.0.dist-info/top_level.txt
odoo13_addon_shopfloor_base-13.0.1.1.0.dist-info/RECORD
