Metadata-Version: 2.1
Name: odoo13-addon-shopfloor-base
Version: 13.0.1.1.0
Summary: Core module for creating mobile apps
Home-page: https://github.com/OCA/wms
Author: Camptocamp, BCIM, Akretion, Odoo Community Association (OCA)
Author-email: support@odoo-community.org
License: LGPL-3
Platform: UNKNOWN
Classifier: Programming Language :: Python
Classifier: Framework :: Odoo
Classifier: License :: OSI Approved :: GNU Lesser General Public License v3 (LGPLv3)
Classifier: Development Status :: 3 - Alpha
Requires-Python: >=3.5
Requires-Dist: odoo13-addon-auth-api-key
Requires-Dist: odoo13-addon-base-jsonify
Requires-Dist: odoo13-addon-base-rest
Requires-Dist: odoo (<13.1dev,>=13.0a)
